jhandu/__init__.py
jhandu-0.1.0.dist-info/METADATA
jhandu-0.1.0.dist-info/WHEEL
jhandu-0.1.0.dist-info/top_level.txt
jhandu-0.1.0.dist-info/RECORD
